Compiled from "DecompileTest.java"
public class jvm.DecompileTest {
  public static java.lang.String s;

//构造方法
  public jvm.DecompileTest();
    Code:
    //加载this
       0: aload_0
       //初始化
       1: invokespecial #1                  // Method java/lang/Object."<init>":()V
       4: return


  public java.lang.String add(int, int);
    Code:
        //第 0个参数 this
        //加载第一个参数
       0: iload_1
        //加载第一个参数
       1: iload_2
       //累计
       2: iadd
       //当int取值-1~5采用iconst指令，取值-128~127采用bipush指令
       3: bipush        100
       5: imul
       //存入变量3
       6: istore_3
       //加载变量3
       7: iload_3
       //获取静态变量
       8: getstatic     #7                  // Field s:Ljava/lang/String;
       //调用方法进行 + 操作
      11: invokedynamic #13,  0             // InvokeDynamic #0:makeConcatWithConstants:(ILjava/lang/String;)Ljava/lang/String;
      16: areturn

  public static void main(java.lang.String[]);
    Code:
       0: return

//静态变量相关
  static {};
    Code:
       0: ldc           #17                 // String @Hello
       //压入静态变量
       2: putstatic     #7                  // Field s:Ljava/lang/String;
       5: return
}
